Metadata-Version: 2.2
Name: image_processing-nathcsm
Version: 0.0.1
Summary: Pacote image_processing-nathcsm
Home-page: https://github.com/nathaliacosim/image-processing-package
Author: Nathalia
Author-email: nathalia.pcosim@gmail.com
Requires-Python: >=3.8
Requires-Dist: matplotlib
Requires-Dist: numpy
Requires-Dist: scikit-image>=0.16.1
Dynamic: author
Dynamic: author-email
Dynamic: description
Dynamic: description-content-type
Dynamic: home-page
Dynamic: requires-dist
Dynamic: requires-python
Dynamic: summary
